{
  "version": "1.0.1",
  "map": {
    "audio": {
      "time": 1781687812284.6128,
      "uuid": "54b3ee86-75d7-4d0f-9ec1-d6056f0048b7"
    },
    "prefabs": {
      "time": 1781687812284.7466,
      "uuid": "6734346e-f6aa-496e-99d3-a430168ee800"
    },
    "scenes": {
      "time": 1781687922604.2888,
      "uuid": "ce198c16-ff4c-4d74-831e-b5e0d330ec90"
    },
    "scripts": {
      "time": 1781748300549.346,
      "uuid": "5a120bf4-ac05-4d4e-91a7-48c60f8c8e71"
    },
    "textures": {
      "time": 1781687812284.9304,
      "uuid": "b81563bb-10c2-4364-a4fb-33b3044e3581"
    },
    "scripts/core": {
      "time": 1781751286219.0764,
      "uuid": "3e7a1e1f-22d7-4715-9ab1-35532df74f70"
    },
    "scripts/game": {
      "time": 1781755086539.8694,
      "uuid": "13d2e497-dec9-4c39-865e-d47d2a7a550b"
    },
    "scripts/ui": {
      "time": 1781751286219.5698,
      "uuid": "0e5d0d4b-7dd5-4acf-8484-4255a10a48da"
    },
    "scripts/core/AudioManager.ts": {
      "time": 1781749379639.279,
      "uuid": "521573d7-df85-44d9-81c2-0236b3ae97f5"
    },
    "scripts/core/GameTypes.ts": {
      "time": 1781755086298.3235,
      "uuid": "58a05250-0e21-4b07-88a4-a3a1530f0bc6"
    },
    "scripts/game/GameManager.ts": {
      "time": 1781755086624.2312,
      "uuid": "7fb0ce1a-d40b-4b3d-92ce-2eed9aa6c1bf"
    },
    "scripts/game/Mole.ts": {
      "time": 1781686974349.4368,
      "uuid": "c9da4686-68f1-4a86-bcbe-2dbbfa5599d6"
    },
    "scripts/game/MoleManager.ts": {
      "time": 1781748511572.6165,
      "uuid": "6a086a09-3145-4a9d-a1a5-7a19622f1db4"
    },
    "scripts/game/ScoreManager.ts": {
      "time": 1781686974200.4202,
      "uuid": "e3548882-4a57-4e76-b53d-f8cfb9f9d77e"
    },
    "scripts/game/TimerManager.ts": {
      "time": 1781686974274.5981,
      "uuid": "54bc61c5-a00a-4254-a9d7-e2b7f40a2c88"
    },
    "scripts/ui/UIManager.ts": {
      "time": 1781755086703.7756,
      "uuid": "d74f25be-f2dc-4f03-9545-0469a5e07b7a"
    },
    "audio.meta": {
      "time": 1781687810978.9863
    },
    "prefabs.meta": {
      "time": 1781687810979.045
    },
    "scenes.meta": {
      "time": 1781687810979.0903
    },
    "scripts.meta": {
      "time": 1781687810979.1333
    },
    "textures.meta": {
      "time": 1781687810979.1758
    },
    "scripts/core.meta": {
      "time": 1781687810979.3882
    },
    "scripts/game.meta": {
      "time": 1781687810979.5112
    },
    "scripts/ui.meta": {
      "time": 1781687810979.616
    },
    "scripts/core/AudioManager.ts.meta": {
      "time": 1781687810980.4553
    },
    "scripts/core/GameTypes.ts.meta": {
      "time": 1781687810980.5747
    },
    "scripts/game/GameManager.ts.meta": {
      "time": 1781687810980.6328
    },
    "scripts/game/Mole.ts.meta": {
      "time": 1781687810980.6873
    },
    "scripts/game/MoleManager.ts.meta": {
      "time": 1781687810980.7405
    },
    "scripts/game/ScoreManager.ts.meta": {
      "time": 1781687810981.8713
    },
    "scripts/game/TimerManager.ts.meta": {
      "time": 1781687810981.9265
    },
    "scripts/ui/UIManager.ts.meta": {
      "time": 1781687810981.9863
    },
    "audio/README.md": {
      "time": 1781687076280.2297,
      "uuid": "55858a77-9a6f-449d-b897-8e546da67935"
    },
    "prefabs/README.md": {
      "time": 1781687076205.5425,
      "uuid": "224069b4-1440-4cb8-b665-6da7ee622736"
    },
    "scenes/README.md": {
      "time": 1781687076132.7317,
      "uuid": "902d7f8f-fd13-4116-8884-148ed0531bcb"
    },
    "textures/README.md": {
      "time": 1781687076355.7551,
      "uuid": "2f1e53c7-7f3c-4533-b5ee-69d6225b7cd3"
    },
    "audio/README.md.meta": {
      "time": 1781687812286.444
    },
    "textures/README.md.meta": {
      "time": 1781687812286.6655
    },
    "prefabs/README.md.meta": {
      "time": 1781687812286.9697
    },
    "scenes/README.md.meta": {
      "time": 1781687812287.0413
    },
    "scenes/Main.scene.meta": {
      "time": 1781687922611.2756
    },
    "scenes/Main.scene": {
      "time": 1781748312434.148,
      "uuid": "4667e568-8ca4-4424-86f7-d4001f56f660"
    },
    "scripts/game/AutoGameBootstrap.ts.meta": {
      "time": 1781688780753.7078
    },
    "scripts/game/AutoGameBootstrap.ts": {
      "time": 1781755117120.539,
      "uuid": "f455209e-7559-4185-83d8-d6e6d6eae97c"
    },
    "resources.meta": {
      "time": 1781690512004.773
    },
    "resources/audio.meta": {
      "time": 1781690512004.8418
    },
    "resources": {
      "time": 1781751286218.4731,
      "uuid": "f2c82ddb-6195-402d-85c5-b6db379cfa4a"
    },
    "resources/audio": {
      "time": 1781751286222.8206,
      "uuid": "bcfab1a1-0cde-4f22-b196-6749d356583f"
    },
    "resources/README.md.meta": {
      "time": 1781690512014.6345
    },
    "resources/audio/sfx_button_click.wav.meta": {
      "time": 1781690512051.469
    },
    "resources/audio/sfx_countdown_end.wav.meta": {
      "time": 1781690512051.7783
    },
    "resources/audio/sfx_game_win.wav.meta": {
      "time": 1781690512051.9014
    },
    "resources/audio/sfx_hit_mole.wav.meta": {
      "time": 1781690512051.2766
    },
    "resources/audio/sfx_mole_appear.wav.meta": {
      "time": 1781690512051.586
    },
    "resources/README.md": {
      "time": 1781689700072.2188,
      "uuid": "851908ca-7f3a-4cea-b8de-20658a131c16"
    },
    "resources/audio/sfx_hit_mole.wav": {
      "time": 1781689562338.112,
      "uuid": "ef717cbe-5deb-437b-b2e9-e50065d536f1"
    },
    "resources/audio/sfx_button_click.wav": {
      "time": 1781689562337.3718,
      "uuid": "6f36a349-fa11-4531-8c2f-c202eb970e2f"
    },
    "resources/audio/sfx_mole_appear.wav": {
      "time": 1781689562337.8286,
      "uuid": "f0f3f42e-918a-4e1d-b342-dc6dc0683954"
    },
    "resources/audio/sfx_countdown_end.wav": {
      "time": 1781689562338.7358,
      "uuid": "3105ae49-57b3-4839-8637-70c0d66e7ca2"
    },
    "resources/audio/sfx_game_win.wav": {
      "time": 1781689562339.5977,
      "uuid": "64e31187-4911-4f14-9679-aa5301aea697"
    },
    "scripts/core/StorageManager.ts.meta": {
      "time": 1781690824631.853
    },
    "scripts/game/ComboManager.ts.meta": {
      "time": 1781690824632.006
    },
    "scripts/core/StorageManager.ts": {
      "time": 1781755086378.5457,
      "uuid": "0db8c77b-ca9b-49b1-a2f8-b1ba487e4b48"
    },
    "scripts/game/ComboManager.ts": {
      "time": 1781690626239.3289,
      "uuid": "e90832bb-a1dc-4c37-bf56-8ed8f7eae545"
    },
    "scripts/platform.meta": {
      "time": 1781748300551.1902
    },
    "scripts/platform/PlatformAdapter.ts.meta": {
      "time": 1781748300552.2363
    },
    "scripts/platform": {
      "time": 1781748300549.897,
      "uuid": "15823214-3586-43fa-a4b0-c2ddb895a75a"
    },
    "scripts/platform/PlatformAdapter.ts": {
      "time": 1781691385426.891,
      "uuid": "67ffeb66-11b5-4c3e-bf76-246f0f52d3a7"
    },
    "resources/textures.meta": {
      "time": 1781751286220.657
    },
    "resources/textures/gameplay.meta": {
      "time": 1781751286220.7178
    },
    "scripts/core/ArtResourceManager.ts.meta": {
      "time": 1781751286221.8918
    },
    "scripts/ui/SafeAreaLayout.ts.meta": {
      "time": 1781751286222.03
    },
    "scripts/ui/TutorialManager.ts.meta": {
      "time": 1781751286222.126
    },
    "resources/textures": {
      "time": 1781751286218.8164,
      "uuid": "08bc91d3-dada-4e93-a0a7-33961ca8faaf"
    },
    "resources/textures/gameplay": {
      "time": 1781751286223.5447,
      "uuid": "7d74922c-2166-4f5a-822f-e016643c255a"
    },
    "scripts/core/ArtResourceManager.ts": {
      "time": 1781748667826.5305,
      "uuid": "d7b36ab9-e20f-4fcb-8f82-4ceff407b673"
    },
    "scripts/ui/SafeAreaLayout.ts": {
      "time": 1781749714610.4453,
      "uuid": "d2469def-3b3f-40fd-a1bd-2e89609ce92d"
    },
    "scripts/ui/TutorialManager.ts": {
      "time": 1781749238868.8801,
      "uuid": "33c3c7ba-3269-44c7-9b81-f0ae678ea4d4"
    },
    "resources/audio/bgm_meadow_loop.mp3.meta": {
      "time": 1781751286296.7344
    },
    "resources/textures/gameplay/gameplay_background.jpg.meta": {
      "time": 1781751286298.91
    },
    "resources/textures/gameplay/hole_wood.png.meta": {
      "time": 1781751286296.1643
    },
    "resources/textures/gameplay/mole_bomb.png.meta": {
      "time": 1781751286297.215
    },
    "resources/textures/gameplay/mole_golden.png.meta": {
      "time": 1781751286297.0103
    },
    "resources/textures/gameplay/mole_normal.png.meta": {
      "time": 1781751286304.504
    },
    "resources/textures/gameplay/hole_wood.png": {
      "time": 1781748462455.642,
      "uuid": "1bab2ed5-c5cb-41a0-b536-1e91e865ba4d"
    },
    "resources/audio/bgm_meadow_loop.mp3": {
      "time": 1781749267968.1309,
      "uuid": "e82ea7d2-ca6a-472d-af2e-564ceda5f38a"
    },
    "resources/textures/gameplay/mole_golden.png": {
      "time": 1781748462165.6787,
      "uuid": "5c287dcf-d1f3-4e8f-bd73-10ef2ea9e744"
    },
    "resources/textures/gameplay/mole_bomb.png": {
      "time": 1781748462308.8835,
      "uuid": "227c0bb5-6e50-419a-be01-0d1f13532686"
    },
    "resources/textures/gameplay/gameplay_background.jpg": {
      "time": 1781748643351.7751,
      "uuid": "a6080fd1-c530-4790-af62-35970b585fab"
    },
    "resources/textures/gameplay/mole_normal.png": {
      "time": 1781748462015.6873,
      "uuid": "47f77cfd-85b0-4092-a0ba-26ba2a5e0189"
    },
    "scripts/game/DailyChallengeManager.ts.meta": {
      "time": 1781755086539.926
    },
    "scripts/game/DailyChallengeManager.ts": {
      "time": 1781755134441.089,
      "uuid": "2ac34fa4-93e0-4a14-9292-b92e3ab34f11"
    }
  },
  "missing": {}
}
